nepal_geo_data/__init__.py
nepal_geo_data/core.py
nepal_geo_data/data/districts.geojson
nepal_geo_data/data/municipalities.geojson
nepal_geo_data/data/provinces.geojson
nepal_geo_data-0.3.3.dist-info/licenses/LICENSE
nepal_geo_data-0.3.3.dist-info/METADATA
nepal_geo_data-0.3.3.dist-info/WHEEL
nepal_geo_data-0.3.3.dist-info/top_level.txt
nepal_geo_data-0.3.3.dist-info/RECORD
