Metadata-Version: 2.4
Name: nepal-geo-data
Version: 0.3.3
Summary: Comprehensive Python package offering Nepal's geographical data including GeoJSON for all 77 districts and 7 provinces. Ideal for GIS, mapping, and data visualization projects for Nepal.
Home-page: https://github.com/bedbyaspokhrel/nepal-geo-data
Author: Bedbyas Pokhrel
Author-email: Bedbyas Pokhrel <bedbyaspokhrel@gmail.com>
License: MIT
Project-URL: Homepage, https://github.com/bedbyaspokhrel/nepal-geo-data
Project-URL: Bug Tracker, https://github.com/bedbyaspokhrel/nepal-geo-data/issues
Keywords: nepal,geojson,gis,nepal-map,districts,provinces,nepal-geography,kathmandu,data-visualization,python-nepal
Classifier: Programming Language :: Python :: 3
Classifier: License :: OSI Approved :: MIT License
Classifier: Operating System :: OS Independent
Classifier: Topic :: Scientific/Engineering :: GIS
Classifier: Intended Audience :: Developers
Classifier: Intended Audience :: Science/Research
Requires-Python: >=3.8
License-File: LICENSE
Dynamic: author
Dynamic: home-page
Dynamic: license-file
Dynamic: requires-python
